{
"How many times have you washed your khakis?":[["Keys",63],["Money",7],["Weight",5],["Contact Lens",4],["Eyeglasses",4],["Wallet",3],["Earring",2]],
"Who is your favorite Upper-Staff member?":[["Doll",39],["Stuffed Animal",13],["Train",11],["Rocking Horse",9],["Toy Soldier",9],["Drum",4],["Ball",3],["Wagon",3]],
"What is the best competition event in the Klenczar Cup or Walling Classic?":[["Corn",37],["Meat",23],["Popcorn",22],["Caramel",6],["Nuts",3],["Peanut Butter",3],["Taffy",2]],
"Which summer sea term port is the best?":[["Fingerprint Them",56],["Book Them",20],["Question",5],["Mug Shot",5],["Give One Phone Call",3],["Put Then in Cell",3],["Read Their Rights",2]],
"What is the best restaurant in Galveston?":[["Pyramids",77],["Sphinx",7],["Camels",4],["Nile River",3],["Desert",3],["Cleopatra",2],["Pharaoh",2],["Mummies",1]],
"What is the most common animal to cross rattlesnake road?":[["Restaurant",26],["Gas Station",24],["Airport",22],["Hospital",7],["Hotel",6],["Mall",6],["Grocery",4]],
"Which day is the worst to have formation?":[["Comb",26],["Spoons",22],["Pots & Pans",10],["Bottle",6],["Grass",5],["Paper",5],["Rubber Band",5],["Box",3],["Table",3],["Broom",2],["Pencil",2],["Wash Tub",2]],
"What is the most common reason for demerits?":[["Dog",29],["Monkey",21],["Dolphin",16],["Cat",14],["Fox",5],["Horse",4],["Parrot",3]],
"Which CO has the most demerits?":[["Underwear",18],["Toilet Paper",9],["Wedding Dress",9],["Milk",8],["Eggs",7],["Bread",6],["Sheets",6],["Flour",5],["Paper",5],["Sugar",3],["Tissues",3],["Socks",3]],
"Who is the best Commandant?":[["Car",42],["Coat",11],["Purse",11],["Dress",8],["Shoes",5],["Robe",3],["Nail Polish",2]],
"Which Maritime Academy is the best party school?":[["Read",53],["Sleep",10],["Eat",9],["Exercise",8],["Watch TV",6],["Drink Coffee",5],["Clean",3]],
"Which Galveston beach is best?":[["Kangaroo",36],["Purse",23],["Pool Table",13],["Bread",10],["Car Door",7],["Diaper Bag",2],["Tool Belt",2]],
"Who has the best mustache in the Corps?":[["Card",46],["Kiss",19],["Cake",15],["Party",6],["Hug",3],["Spanking",3],["Call",2]],
"Who is the best professor at TAMUG":[["Post Office",50],["Store",14],["Bank",9],["Hospital",7],["Dry Cleaners",6],["Airport",5],["School",5]],
"What is the best sandwich on the Mess Deck menu?":[["Plumbing",19],["Roof",17],["Cost",10],["Termites",9],["Neighborhood",8],["Furnace",7],["Title",7],["Construction",6],["Wiring",3],["Schools",2],["Interest Rate",2]],
"What is the best Aggie yell?":[["Candy",62],["Fruit",15],["Coal",5],["Perfume",5],["Money",3],["Toys",3],["Nuts",3]],
"Where is the best place to eat on campus?":[["Car",35],["House",35],["Hair",15],["Face",3],["Body",2],["Clothing",2],["Yard",2]],
"What is the best PT activity?":[["Sing",34],["Make Faces",23],["Play With It",9],["Talk To It",8],["Rock It",6],["Make Funny Noises",5],["Shake a Rattle",4],["Bounce",3],["Tickle",2],["Peek A Boo",2]],
"Which TAMMAH hallway is the best?":[["Pro Athlete",46],["Lifeguard",13],["Actor",10],["TV Show Host",8],["Cruise Director",3],["Musician",3],["Clown",2],["Gym Teacher",2],["Sports Coach",2],["Travel Guide",2]],
"What is the best item on the Whataburger menu?":[["Garden",26],["Swimming",24],["Walk",14],["Cookout",6],["Sunbathing",5],["Bicycling",4],["Picnic",3],["Golf",3]],
"What company has the most demerits?":[["Sales Clerk",33],["Police",14],["Flight Attendant",7],["Waiter",6],["Telephone Operator",5],["Hotel Clerk",4],["Banker",3],["Nurse",3]],
"What truck brand is the best?":[["Teeth",21],["Glasses",16],["Bathroom",13],["Car",9],["Dishes",7],["Silverware",6],["Windows",6],["House",5],["Kitchen",3],["Sink",3]],
"Which maritime meme account is the best?":[["Mercedes",27],["Cadillac",26],["BMW",14],["Lincoln",9],["Rolls Royce",8],["Porsche",7],["Corvette",4]],
"When is the best time to have watch in port or at sea?":[["Body",52],["Salad",30],["Frying Pan",4],["Door Hinges",3],["Hair",3],["Furniture",2]],
"What company has the highest GPA?":[["VCR",54],["Microwave",29],["Stove",6],["Radio",5],["TV",4]],
"What is the most common item picked up during parking lot clean-up?":[["Las Vegas",24],["Sodom",19],["New Orleans",13],["New York City",10],["San Francisco",8],["Rome",5]],
}
